common/__init__.py
common/decos.py
common/descryptors.py
common/errors.py
common/metaclasses.py
common/utils.py
common/variables.py
logs/__init__.py
logs/config_client_log.py
logs/config_server_log.py
server/__init__.py
server/add_user.py
server/config_window.py
server/core.py
server/database.py
server/main_window.py
server/remove_user.py
server/stat_window.py
My_Server_Chat_129m-1.0.dist-info/METADATA
My_Server_Chat_129m-1.0.dist-info/WHEEL
My_Server_Chat_129m-1.0.dist-info/top_level.txt
My_Server_Chat_129m-1.0.dist-info/RECORD
