Metadata-Version: 2.1
Name: My-Server-Chat-129m
Version: 1.0
Summary: Server Chat
Requires-Dist: PyQt5
Requires-Dist: sqlalchemy
Requires-Dist: pycryptodome
